LICENSE
MANIFEST.in
README.md
setup.py
nixodmlconverter/__init__.py
nixodmlconverter/convert.py
nixodmlconverter/info.json
nixodmlconverter/info.py
nixodmlconverter.egg-info/PKG-INFO
nixodmlconverter.egg-info/SOURCES.txt
nixodmlconverter.egg-info/dependency_links.txt
nixodmlconverter.egg-info/entry_points.txt
nixodmlconverter.egg-info/requires.txt
nixodmlconverter.egg-info/top_level.txt
test/test_convert.py