Metadata-Version: 2.1
Name: nixodmlconverter
Version: 0.0.7
Summary: Converter between NIX and odML format
Home-page: https://github.com/G-Node/nix-odml-converter
Author: Achilleas Koutsou, Julia Sprenger, Michael Sonntag
Author-email: dev@g-node.org
License: BSD
Platform: UNKNOWN
Classifier: Development Status :: 4 - Beta
Classifier: Programming Language :: Python
Classifier: Programming Language :: Python :: 3.6
Classifier: Programming Language :: Python :: 3.7
Classifier: Programming Language :: Python :: 3.8
Classifier: Topic :: Scientific/Engineering
Classifier: Intended Audience :: Science/Research
Classifier: License :: OSI Approved :: BSD License
